Metadata-Version: 1.1
Name: dash-calendar
Version: 0.0.3
Summary: a calendar datepicker component for dash
Home-page: UNKNOWN
Author: fusoyo <fengchuyao20@gmail.com>
Author-email: UNKNOWN
License: MIT
Platform: UNKNOWN
Classifier: Framework :: Dash
